pytorch_nanopi/__init__.py
pytorch_nanopi/torch/_C.cpython-36m-aarch64-linux-gnu.so
pytorch_nanopi/torch/_C.so
pytorch_nanopi/torch/__config__.py
pytorch_nanopi/torch/__future__.py
pytorch_nanopi/torch/__init__.py
pytorch_nanopi/torch/_classes.py
pytorch_nanopi/torch/_dl.cpython-36m-aarch64-linux-gnu.so
pytorch_nanopi/torch/_dl.so
pytorch_nanopi/torch/_jit_internal.py
pytorch_nanopi/torch/_namedtensor_internals.py
pytorch_nanopi/torch/_ops.py
pytorch_nanopi/torch/_overrides.py
pytorch_nanopi/torch/_six.py
pytorch_nanopi/torch/_storage_docs.py
pytorch_nanopi/torch/_tensor_docs.py
pytorch_nanopi/torch/_tensor_str.py
pytorch_nanopi/torch/_torch_docs.py
pytorch_nanopi/torch/_utils.py
pytorch_nanopi/torch/_utils_internal.py
pytorch_nanopi/torch/functional.py
pytorch_nanopi/torch/hub.py
pytorch_nanopi/torch/quasirandom.py
pytorch_nanopi/torch/random.py
pytorch_nanopi/torch/serialization.py
pytorch_nanopi/torch/storage.py
pytorch_nanopi/torch/tensor.py
pytorch_nanopi/torch/version.py
pytorch_nanopi/torchvision/__init__.py
pytorch_nanopi/torchvision/utils.py
pytorch_nanopi-0.6.9.dist-info/LICENSE.txt
pytorch_nanopi-0.6.9.dist-info/METADATA
pytorch_nanopi-0.6.9.dist-info/WHEEL
pytorch_nanopi-0.6.9.dist-info/top_level.txt
pytorch_nanopi-0.6.9.dist-info/RECORD
