Metadata-Version: 2.1
Name: pytorch-nanopi
Version: 0.6.9
Summary: This is a package for torch on nano system
Home-page: https://github.com/NocoldBob/pytorch/nano
Author: fastbiubiu
Author-email: fastbiubiu@163.com
License: UNKNOWN
Platform: UNKNOWN
Classifier: Programming Language :: Python :: 3
Classifier: License :: OSI Approved :: MIT License
Classifier: Operating System :: OS Independent
